pyfoobar2k/__init__.py
pyfoobar2k/foobarhttp.py
pyfoobar2k-0.2.6.dist-info/LICENSE
pyfoobar2k-0.2.6.dist-info/METADATA
pyfoobar2k-0.2.6.dist-info/WHEEL
pyfoobar2k-0.2.6.dist-info/top_level.txt
pyfoobar2k-0.2.6.dist-info/RECORD
