Metadata-Version: 2.1
Name: pyfoobar2k
Version: 0.2.6
Summary: control foobar2000 via foo_httpcontrol
Home-page: https://gitlab.com/ed0zer-projects/pyfoobar2k
Author: Edo Ozer
Author-email: ed0zer@gmail.com
License: MIT
Keywords: pyfoobar2k,foo_httpcontrol,foobar2000
Platform: UNKNOWN
Classifier: License :: OSI Approved :: MIT License
Classifier: Programming Language :: Python :: 3.6
Requires-Dist: requests
